{
  "schemaVersion": 1,
  "generatedAt": "2026-07-08",
  "status": "reference-result",
  "strategy": {
    "name": "需給B / 買い75 / 売り65 / 20MA割れ",
    "universe": "日経225",
    "period": "2025年データ",
    "buyScore": 75,
    "sellScore": 65,
    "maxPositions": 5,
    "tradeCostRoundTrip": 0.002,
    "supplyRule": "信用倍率の軽さを60%、52週高値への近さを40%で評価する需給設定です。",
    "exitRules": [
      "スコア65点以下",
      "20日移動平均割れ"
    ]
  },
  "data": {
    "price": "価格履歴",
    "membership": "日経225採用履歴",
    "margin": "信用倍率",
    "excluded": "ニュース件数とTDnet/業績イベントは未反映"
  },
  "result": {
    "annualReturn": 0.85,
    "maxDrawdown": -0.132,
    "sharpeRatio": 2.43,
    "cumulativeWinRate": 0.471,
    "trades": 85,
    "benchmarkAnnualReturnDelta": 0.705,
    "benchmarkDrawdownImprovement": 0.131
  },
  "kpis": [
    {
      "label": "年率リターン",
      "value": 0.85,
      "format": "signedPercent"
    },
    {
      "label": "最大下落率",
      "value": -0.132,
      "format": "signedPercent"
    },
    {
      "label": "シャープレシオ",
      "value": 2.43,
      "format": "number"
    },
    {
      "label": "累積勝率",
      "value": 0.471,
      "format": "percent"
    },
    {
      "label": "取引回数",
      "value": 85,
      "format": "count"
    }
  ],
  "notes": [
    "日経225単純保有との比較では、年率リターンは約+70.5pt、最大下落率は約13.1pt改善。",
    "過去検証であり、将来の成績を保証するものではありません。"
  ]
}
